{
    "version": 1,
    "script_version": "3.5.504",
    "aliases": {},
    "settings": {
        "advanced_settings": true,
        "favorite_settings": [
            "key_users",
            "hidden_badges",
            "chat_font_size"
        ],
        "fix_color": 6,
        "color_blind": "0",
        "show_badges": false,
        "loyalty_badges": false,
        "hidden_badges": [
            "premium",
            "bits",
            "game",
            "turbo",
            "subscriber"
        ],
        "show_deleted_links": true,
        "bits_tags_container": false,
        "bits_redesign": true,
        "auto_theater": true,
        "hosted_channels": false,
        "stream_host_button": false,
        "hide_channel_banner": 2,
        "theater_stats": 1,
        "player_stats": 10,
        "player_volume_bar": true,
        "right_column_width": 250,
        "replace_bad_emotes": false,
        "parse_emoticons": true,
        "banned_words": [
            "anneBurger"
        ],
        "key_users": [],
        "link_image_hover": true,
        "chat_rows": 3,
        "chat_separators": 2,
        "chat_padding": true,
        "emoji_scale": 0,
        "chat_font_size": 14,
        "minimal_chat": 1,
        "chat_delay": 0,
        "prevent_clear": true,
        "hide_conversations_in_theatre": true,
        "minimize_conversations": true,
        "highlight_messages_with_mod_card": true,
        "chat_hover_pause": 4,
        "timeout_notices": 2,
        "input_complete_keys": true,
        "input_complete_name_require_at": true,
        "enable_recommended_vods": false,
        "recommended_above_hosts": false,
        "sidebar_hide_recommended_channels": true,
        "sidebar_hide_prime": 2,
        "sidebar_hide_promoted_games": true,
        "sidebar_hide_recommended_friends": true,
        "sidebar_hide_friends_collapsed": true,
        "sidebar_hide_more_at_twitch": true,
        "sidebar_disable_friends": true,
        "sidebar_directly_to_followed_channels": true,
        "twitch_chat_dark": false,
        "dark_twitch": true,
        "dark_no_blue": true,
        "follow_buttons": false,
        "global_emotes_in_menu": true,
        "emote_menu_collapsed": [
            "twitch-19194",
            "twitch-inventory"
        ],
        "metadata_schedule": false
    }
}